pydao/__init__.py
pydao/dao.py
pydao-0.2.dist-info/DESCRIPTION.rst
pydao-0.2.dist-info/METADATA
pydao-0.2.dist-info/RECORD
pydao-0.2.dist-info/WHEEL
pydao-0.2.dist-info/metadata.json
pydao-0.2.dist-info/top_level.txt
