Metadata-Version: 2.0
Name: pydao
Version: 0.2
Summary: simple mysql access api based on sqlalchemy and pymysql
Home-page: https://github.com/yimian/pydao
Author: zhangjinjie
Author-email: zhangjinjie@yimian.com.cn
License: UNKNOWN
Platform: UNKNOWN
Requires-Dist: future
Requires-Dist: pymysql
Requires-Dist: sqlalchemy
